sbom.xml
seman/__init__.py
seman/main.py
seman-0.1.3.dist-info/entry_points.txt
seman-0.1.3.dist-info/LICENSE
seman-0.1.3.dist-info/WHEEL
seman-0.1.3.dist-info/METADATA
seman-0.1.3.dist-info/RECORD
