Metadata-Version: 2.1
Name: seman
Version: 0.1.3
Summary: 
Home-page: https://github.com/kannkyo/seman
Keywords: Semantic Versioning
Author: kannkyo
Author-email: 15080890+kannkyo@users.noreply.github.com
Requires-Python: >=3.8,<4.0
Classifier: Programming Language :: Python :: 3
Classifier: Programming Language :: Python :: 3.8
Classifier: Programming Language :: Python :: 3.9
Classifier: Programming Language :: Python :: 3.10
Classifier: Programming Language :: Python :: 3.11
Classifier: Topic :: Software Development :: Libraries :: Python Modules
Requires-Dist: cyclonedx-bom (>=3.11.0,<4.0.0)
Requires-Dist: fire (>=0.5.0,<0.6.0)
Requires-Dist: toml (>=0.10.2,<0.11.0)
Project-URL: Documentation, https://github.com/kannkyo/seman
Project-URL: Repository, https://github.com/kannkyo/seman
